uppsala_pyub/__init__.py
uppsala_pyub/bibtex.py
uppsala_pyub/cli.py
uppsala_pyub/handle_results.py
uppsala_pyub/query.py
uppsala_pyub/soup.py
uppsala_pyub-0.3.0.dist-info/METADATA
uppsala_pyub-0.3.0.dist-info/WHEEL
uppsala_pyub-0.3.0.dist-info/entry_points.txt
uppsala_pyub-0.3.0.dist-info/RECORD
