Metadata-Version: 2.1
Name: uppsala-pyub
Version: 0.3.0
Summary: A python module and CLI to facilitate searching Uppsala University's catalog.
License: GPLv3
Author: bobborges
Requires-Python: >=3.12,<4.0
Classifier: License :: Other/Proprietary License
Classifier: Programming Language :: Python :: 3
Classifier: Programming Language :: Python :: 3.12
Classifier: Programming Language :: Python :: 3.13
Requires-Dist: beautifulsoup4
Requires-Dist: lxml_html_clean
Requires-Dist: requests
Requires-Dist: requests_html
